README.md
setup.cfg
setup.py
pyfawkes/__init__.py
pyfawkes/__main__.py
pyfawkes/commandline.py
pyfawkes/loader.py
pyfawkes/mutator.py
pyfawkes/runner.py
pyfawkes/utils.py
pyfawkes.egg-info/PKG-INFO
pyfawkes.egg-info/SOURCES.txt
pyfawkes.egg-info/dependency_links.txt
pyfawkes.egg-info/not-zip-safe
pyfawkes.egg-info/requires.txt
pyfawkes.egg-info/top_level.txt
pyfawkes/operators/__init__.py
pyfawkes/operators/arithmetic.py
pyfawkes/operators/constant.py
pyfawkes/operators/delete.py
pyfawkes/operators/logical.py
pyfawkes/operators/loop.py
pyfawkes/operators/misc.py