Metadata-Version: 2.1
Name: pyfawkes
Version: 0.1.1
Summary: ''
Home-page: https://github.com/MarkCBell/pyfawkes
Author: Mark Bell
Author-email: mcbell@illinois.edu
License: MIT
Keywords: mutation testing
Platform: UNKNOWN
Classifier: Development Status :: 3 - Alpha
Classifier: Intended Audience :: Education
Classifier: Intended Audience :: Science/Research
Classifier: License :: OSI Approved :: MIT License
Classifier: Natural Language :: English
Classifier: Operating System :: OS Independent
Classifier: Programming Language :: Python
Classifier: Topic :: Software Development :: Testing
Requires-Python: >=3.5
